{
  "id1": {
    "Понедельник": {
      "12:10": "позавтракать",
      "14:05": "сделать пробежку",
      "14:09": "выйти из дома на работу",
      "11:56": "пообедать",
      "23:50": "пойти погулять и съесть мороженое"
    },
    "Вторник": {
      "11:50": "работа",
      "11:52": "прогулка в парке",
      "12:58": "посмотреть новости",
      "11:56": "покормить кота",
      "15:30": "бассейн"
    },
    "Среда": {
      "11:50": "работа",
      "11:52": "прогулка в парке",
      "12:58": "посмотреть новости",
      "11:56": "покормить кота",
      "15:30": "бассейн"
    },
    "Четверг": {
      "11:50": "работа",
      "11:52": "прогулка в парке",
      "12:58": "посмотреть новости",
      "11:56": "покормить кота",
      "15:30": "бассейн"
    },
    "Пятница": {
      "11:50": "работа",
      "11:52": "прогулка в парке",
      "12:58": "посмотреть новости",
      "11:56": "покормить кота",
      "15:30": "бассейн"
    },
    "Суббота": {
      "11:50": "работа",
      "11:52": "прогулка в парке",
      "12:58": "посмотреть новости",
      "11:56": "покормить кота",
      "15:30": "бассейн"
    },
    "Воскресенье": {
      "11:50": "работа",
      "11:52": "прогулка в парке",
      "12:58": "посмотреть новости",
      "11:56": "покормить кота",
      "15:30": "бассейн"
    }
  },
  "id2": {
    "Понедельник": {
      "14:00": "позавтракать",
      "14:05": "сделать пробежку",
      "14:07": "выйти из дома на работу",
      "11:56": "обед",
      "13:30": "пойти погулять и съесть мороженое"
    },
    "Вторник": {
      "11:50": "работа",
      "11:52": "прогулка в парке",
      "12:58": "посмотреть новости",
      "11:56": "покормить кота",
      "15:30": "бассейн"
    }
  },
  "id3": {
    "Понедельник": {
      "14:00": "позавтракать",
      "14:05": "сделать пробежку",
      "14:07": "выйти из дома на работу",
      "11:56": "обед",
      "13:30": "пойти погулять и съесть мороженое"
    },
    "Вторник": {
      "11:50": "работа",
      "11:52": "прогулка в парке",
      "12:58": "посмотреть новости",
      "11:56": "покормить кота",
      "15:30": "бассейн"
    }
  }
}